packaging_my_first/__init__.py
packaging_my_first/double.py
python_packaging_my_first_package-0.1.1.dist-info/METADATA
python_packaging_my_first_package-0.1.1.dist-info/WHEEL
python_packaging_my_first_package-0.1.1.dist-info/RECORD
