Metadata-Version: 2.1
Name: python-packaging-my-first-package
Version: 0.1.1
Summary: Testing
Author: Instauro
Requires-Python: >=3.11,<4.0
Classifier: Programming Language :: Python :: 3
Classifier: Programming Language :: Python :: 3.11
Requires-Dist: requests (>=2.31.0,<3.0.0)
Requires-Dist: tqdm (>=4.65.0,<5.0.0)
